MANIFEST.in
README
setup.py
django_featured.egg-info/PKG-INFO
django_featured.egg-info/SOURCES.txt
django_featured.egg-info/dependency_links.txt
django_featured.egg-info/top_level.txt
django_featured.egg-info/zip-safe
featured/__init__.py
featured/admin.py
featured/managers.py
featured/models.py
featured/urls.py
featured/views.py
featured/templatetags/__init__.py
featured/templatetags/featured_tags.py