Metadata-Version: 1.0
Name: django-featured
Version: 0.1.6
Summary: An application for starting new django applications.
Home-page: http://github.com/powellc/django-featured
Author: Colin Powell
Author-email: colin@onecardinal.com
License: BSD
Download-URL: http://github.com/powellc/django-featured/downloads
Platform: UNKNOWN
Classifier: Development Status :: 3 - Alpha
Classifier: Environment :: Web Environment
Classifier: Intended Audience :: Developers
Classifier: License :: OSI Approved :: BSD License
Classifier: Operating System :: OS Independent
Classifier: Programming Language :: Python
Classifier: Framework :: Django
